pdc_session/__init__.py
pdc_session/api/client.py
pdc_session/api/session.py
pdc_session/helpers/concurent.py
pdc_session/helpers/logger.py
pdc_session/helpers/singleton.py
pdc_session/session_config.py
pdc_session/session_persist.py
pdc_session/storage/__init__.py
pdc_session/storage/cloud_storage.py
pdc_session/storage/local_storage.py
pdc_session/storage/mixed_storage.py
pdc_session/types/__init__.py
pdc_session/types/client.py
pdc_session/types/session.py
pdc_session/types/session_exception.py
pdc_session-0.1.19.dist-info/WHEEL
pdc_session-0.1.19.dist-info/METADATA
pdc_session-0.1.19.dist-info/RECORD
