Metadata-Version: 2.1
Name: pdc-session
Version: 0.1.19
Summary: simple shopee session manager
Author: Hfrada
Author-email: madefrada@gmail.com
Requires-Python: >=3.9,<4.0
Classifier: Programming Language :: Python :: 3
Classifier: Programming Language :: Python :: 3.10
Classifier: Programming Language :: Python :: 3.9
Requires-Dist: ecceran (==0.1.1)
Requires-Dist: requests (>=2,<3)
